odoo/addons/contract_variable_qty_prorated/README.rst
odoo/addons/contract_variable_qty_prorated/__init__.py
odoo/addons/contract_variable_qty_prorated/__manifest__.py
odoo/addons/contract_variable_qty_prorated/data/contract_variable_qty_prorated.xml
odoo/addons/contract_variable_qty_prorated/i18n/contract_variable_qty_prorated.pot
odoo/addons/contract_variable_qty_prorated/i18n/fr.po
odoo/addons/contract_variable_qty_prorated/i18n/pt_BR.po
odoo/addons/contract_variable_qty_prorated/models/__init__.py
odoo/addons/contract_variable_qty_prorated/models/contract_line.py
odoo/addons/contract_variable_qty_prorated/readme/CONTRIBUTORS.rst
odoo/addons/contract_variable_qty_prorated/readme/DESCRIPTION.rst
odoo/addons/contract_variable_qty_prorated/readme/ROADMAP.rst
odoo/addons/contract_variable_qty_prorated/static/description/icon.png
odoo/addons/contract_variable_qty_prorated/static/description/index.html
odoo/addons/contract_variable_qty_prorated/tests/__init__.py
odoo/addons/contract_variable_qty_prorated/tests/test_compute_proprata.py
odoo/addons/contract_variable_qty_prorated/views/abstract_contract_view.xml
odoo12_addon_contract_variable_qty_prorated-12.0.1.1.1.dist-info/METADATA
odoo12_addon_contract_variable_qty_prorated-12.0.1.1.1.dist-info/WHEEL
odoo12_addon_contract_variable_qty_prorated-12.0.1.1.1.dist-info/top_level.txt
odoo12_addon_contract_variable_qty_prorated-12.0.1.1.1.dist-info/RECORD
